django_chronos/.DS_Store
django_chronos/__init__.py
django_chronos/checks.py
django_chronos/middleware.py
django_chronos/templates/chronos/chronos.html
django_chronos-250808.dist-info/WHEEL
django_chronos-250808.dist-info/METADATA
django_chronos-250808.dist-info/RECORD
