Metadata-Version: 2.3
Name: django-chronos
Version: 250808
Summary: Django middleware that shows you how fast your pages load, right in your browser.
Author: Jonathan Peacher
License: MIT
Requires-Dist: django>=4.2
Project-URL: Issues, https://github.com/djpeacher/django-chronos/issues
Project-URL: Repository, https://github.com/djpeacher/django-chronos
